<MightyFlight>
<BaseLat>52.4800</BaseLat>
<BaseLng>-1.9100</BaseLng>
<AirportName>Birmingham Internaitional</AirportName>
<CityName>Birmingham</CityName>
<Keywords>egbb birmingham uk</Keywords>
<Destinations>
57.149717,-2.094278,Aberdeen;
38.3459963,-0.4906855,Alicante;
36.838976,-2.4610949,Almería;
52.3702157,4.895167900000001,Amsterdam;
36.88414,30.70563,Antalya;
37.9333333,58.3666667,Ashgabat;
43.906667,4.901943999999999,Avignon/Caumont;
54.59728500000001,-5.93012,Belfast;
54.59728500000001,-5.93012,Belfast;
44.818709,0.519103,Bergerac/Roumanière;
43.472009,-1.531372,Biarritz/Anglet/Bayonne;
37.035339,27.43029,Bodrum;
44.830324,-0.701253,Bordeaux/Mérignac;
48.1458923,17.1071373,Bratislava;
48.4434969,-4.420151199999999,Brest/Guipavas;
50.8503396,4.3517103,Brussels;
42.50479259999999,27.4626361,Burgas;
53.12348040000001,18.0084378,Bydgoszcz;
21.158964,-86.84593699999999,Cancún;
54.07623599999999,-4.656918,Castletown;
32.7765656,-79.93092159999999,Charleston;
55.6760968,12.5683371,Copenhagen;
51.8968917,-8.4863157,Cork;
36.7666667,28.8,Dalaman;
54.9966124,-7.3085748,Derry;
25.271139,55.307485,Dubai;
53.3498053,-6.2603097,Dublin;
42.6506652,18.0944232,Dubrovnik;
56.462018,-2.970721,Dundee;
51.2277411,6.7734556,Düsseldorf;
55.953252,-3.188267,Edinburgh;
16.7541667,-22.9458333,Espargos;
37.0193548,-7.9304397,Faro;
50.1109221,8.6821267,Frankfurt-am-Main;
28.3587436,-14.053676,Fuerteventura Island;
32.6669328,-16.9240554,Funchal;
54.35202520000001,18.6466384,Gdańsk;
41.9794005,2.8214264,Girona;
55.864237,-4.251806,Glasgow;
57.70887,11.97456,Gothenburg;
27.9202202,-15.5474373,Gran Canaria Island;
53.5510846,9.9936818,Hamburg;
52.3758916,9.732010400000002,Hannover;
35.3387352,25.1442126,Heraklion;
27.2578957,33.8116067,Hurghada;
38.90895099999999,1.428115,Ibiza;
57.477773,-4.224721,Inverness;
41.00527,28.97696,Istanbul;
38.41885,27.12872,İzmir;
50.26489189999999,19.0237815,Katowice;
54.8984964,23.9035416,Kaunas;
41.025913,24.405449,Kavala;
38.1753675,20.5692179,Kefallinia Island;
39.6118388,19.8306051,Kerkyra Island;
36.7998512,27.1029431,Kos Island;
50.06465009999999,19.9449799,Kraków;
46.1911105,-1.3944629,La Rochelle/Île de Ré;
29.0468535,-13.5899733,Lanzarote Island;
34.9166667,33.6333333,Larnarca;
45.860833,1.180278,Limoges/Bellegarde;
35.859757,14.488362,Luqa;
25.6872431,32.6396357,Luxor;
45.764043,4.835659,Lyon;
36.721261,-4.4212655,Málaga;
39.9496287,4.1104449,Menorca Island;
45.4654542,9.186516,Milan;
35.77718,10.8261,Monastir;
18.4666667,-77.9166667,Montego Bay;
48.1367203,11.576754,Munich;
40.8517746,14.2681244,Nápoli;
40.735657,-74.1723667,Newark;
54.978252,-1.61778,Newcastle;
43.696036,7.265592,Nice;
28.5383355,-81.3792365,Orlando;
39.57119,2.646634,Palma De Mallorca;
34.7720133,32.4297369,Paphos;
48.856614,2.3522219,Paris;
42.7407863,2.8686492,Perpignan/Rivesaltes;
41.1566892,-8.6239254,Porto;
44.8666232,13.8495788,Pula;
18.5333333,-68.3666667,Punta Cana;
48.062495,-1.738984,Rennes/Saint-Jacques;
41.1498259,1.1055321,Reus;
36.163149,27.9717606,Rodes Island;
50.04094689999999,21.9992806,Rzeszów;
49.1868225,-2.1065682,Saint Helier;
49.4541677,-2.5497069,Saint Peter Port;
37.8054749,-0.8379313,San Javier;
36.3931562,25.4615092,Santorini Island;
34.3431937,-85.0783625,Shannon;
27.9158175,34.3299505,Sharm el-Sheikh;
39.1626627,23.4909759,Skiathos;
43.5081323,16.4401935,Split;
48.7754181,9.181758799999999,Stuttgart;
29.49256789999999,34.8949027,Taba;
35.696216,51.422945,Tehran;
28.2915637,-16.6291304,Tenerife Island;
43.653226,-79.3831843,Toronto;
43.6175586,1.4078807,Toulouse/Blagnac;
45.6495354,13.7779716,Trieste;
52.25227,-7.127205999999999,Waterford;
51.6266679,6.1968442,Weeze;
37.7911386,20.7837673,Zakynthos Island;
47.3686498,8.539182499999999,Zurich;
</Destinations>
</MightyFlight>